leaguepedia_parser_thomasbarrepitous/__init__.py
leaguepedia_parser_thomasbarrepitous/logger.py
leaguepedia_parser_thomasbarrepitous/parsers/champions_parser.py
leaguepedia_parser_thomasbarrepitous/parsers/contracts_parser.py
leaguepedia_parser_thomasbarrepitous/parsers/game_parser.py
leaguepedia_parser_thomasbarrepitous/parsers/items_parser.py
leaguepedia_parser_thomasbarrepitous/parsers/player_parser.py
leaguepedia_parser_thomasbarrepitous/parsers/roster_changes_parser.py
leaguepedia_parser_thomasbarrepitous/parsers/scoreboard_players_parser.py
leaguepedia_parser_thomasbarrepitous/parsers/standings_parser.py
leaguepedia_parser_thomasbarrepitous/parsers/team_parser.py
leaguepedia_parser_thomasbarrepitous/parsers/tournament_roster_parser.py
leaguepedia_parser_thomasbarrepitous/site/leaguepedia.py
leaguepedia_parser_thomasbarrepitous/transmuters/field_names.py
leaguepedia_parser_thomasbarrepitous/transmuters/game.py
leaguepedia_parser_thomasbarrepitous/transmuters/game_players.py
leaguepedia_parser_thomasbarrepitous/transmuters/picks_bans.py
leaguepedia_parser_thomasbarrepitous/transmuters/tournament.py
leaguepedia_parser_thomasbarrepitous-0.1.1.dist-info/LICENSE
leaguepedia_parser_thomasbarrepitous-0.1.1.dist-info/METADATA
leaguepedia_parser_thomasbarrepitous-0.1.1.dist-info/WHEEL
leaguepedia_parser_thomasbarrepitous-0.1.1.dist-info/RECORD
