Metadata-Version: 2.3
Name: leaguepedia_parser_thomasbarrepitous
Version: 0.1.1
Summary: Advanced League of Legends esports analytics library with player performance statistics, contract tracking, and comprehensive tournament data
License: MIT
Keywords: leaguepedia,league-of-legends,esports,analytics,performance-statistics,player-data,gaming,riot-games,tournaments,contracts,kda,fantasy-sports
Author: ThomasBP
Author-email: barrepitousthomas@gmail.com
Requires-Python: >=3.9,<4.0
Classifier: Development Status :: 4 - Beta
Classifier: Intended Audience :: Developers
Classifier: Intended Audience :: Science/Research
Classifier: License :: OSI Approved :: MIT License
Classifier: Operating System :: OS Independent
Classifier: Programming Language :: Python :: 3
Classifier: Programming Language :: Python :: 3.9
Classifier: Programming Language :: Python :: 3.10
Classifier: Programming Language :: Python :: 3.11
Classifier: Programming Language :: Python :: 3.12
Classifier: Programming Language :: Python :: 3.13
Classifier: Topic :: Games/Entertainment
Classifier: Topic :: Internet :: WWW/HTTP :: Dynamic Content
Classifier: Topic :: Scientific/Engineering :: Information Analysis
Classifier: Topic :: Software Development :: Libraries :: Python Modules
Requires-Dist: lol-dto (>=2.0.0,<3.0.0)
Requires-Dist: lol-id-tools (>=2.0.0,<3.0.0)
Requires-Dist: mwclient (>=0.10.1,<0.11.0)
Requires-Dist: mwrogue (>=0.1.0,<0.2.0)
Requires-Dist: rapidfuzz (<3.0)
Project-URL: Documentation, https://github.com/thomasbarrepitous/leaguepedia_parser#readme
Project-URL: Homepage, https://github.com/thomasbarrepitous/leaguepedia_parser
Project-URL: Repository, https://github.com/thomasbarrepitous/leaguepedia_parser
